lightweight_charts/__init__.py
lightweight_charts/abstract.py
lightweight_charts/chart.py
lightweight_charts/drawings.py
lightweight_charts/polygon.py
lightweight_charts/table.py
lightweight_charts/toolbox.py
lightweight_charts/topbar.py
lightweight_charts/util.py
lightweight_charts/widgets.py
lightweight_charts/js/bundle.js
lightweight_charts/js/index.html
lightweight_charts/js/lightweight-charts.standalone.development.js
lightweight_charts/js/styles.css
lightweight_charts_v5-1.0.2.dist-info/licenses/LICENSE
lightweight_charts_v5-1.0.2.dist-info/METADATA
lightweight_charts_v5-1.0.2.dist-info/WHEEL
lightweight_charts_v5-1.0.2.dist-info/top_level.txt
lightweight_charts_v5-1.0.2.dist-info/RECORD
