Metadata-Version: 2.4
Name: lightweight-charts-v5
Version: 1.0.2
Summary: Python framework for TradingView's Lightweight Charts JavaScript library (v5.x).
Home-page: https://github.com/louisnw01/lightweight-charts-python
Author: louisnw
Author-email: louisnw <louisnw@mail.com>
License: MIT License
Project-URL: Homepage, https://github.com/louisnw01/lightweight-charts-python
Project-URL: Repository, https://github.com/louisnw01/lightweight-charts-python
Project-URL: Documentation, https://github.com/louisnw01/lightweight-charts-python/blob/main/README.md
Requires-Python: >=3.8
License-File: LICENSE
Requires-Dist: pandas
Requires-Dist: pywebview>=5.0.5
Dynamic: author
Dynamic: home-page
Dynamic: license-file
Dynamic: requires-python
